pubquiz/__init__.py
pubquiz/__main__.py
pubquiz/api.py
pubquiz/cli.py
pubquiz/py.typed
pubquiz/question.py
pubquiz/quiz.py
pubquiz/round.py
pubquiz/slides.py
pubquiz/version.py
pubquiz/latex_templates/.gitignore
pubquiz/latex_templates/__init__.py
pubquiz/latex_templates/beamer_header.tex
pubquiz/latex_templates/indent.log
pubquiz/latex_templates/photo.png
pubquiz/latex_templates/sheets_header.aux
pubquiz/latex_templates/sheets_header.fdb_latexmk
pubquiz/latex_templates/sheets_header.fls
pubquiz/latex_templates/sheets_header.log
pubquiz/latex_templates/sheets_header.tex
pubquiz/latex_templates/slides_header.aux
pubquiz/latex_templates/slides_header.fdb_latexmk
pubquiz/latex_templates/slides_header.fls
pubquiz/latex_templates/slides_header.log
pubquiz/latex_templates/slides_header.tex
pubquiz/latex_templates/slides_preamble.tex
pubquiz-0.0.5.dist-info/LICENSE
pubquiz-0.0.5.dist-info/METADATA
pubquiz-0.0.5.dist-info/WHEEL
pubquiz-0.0.5.dist-info/entry_points.txt
pubquiz-0.0.5.dist-info/top_level.txt
pubquiz-0.0.5.dist-info/RECORD
