Metadata-Version: 2.1
Name: pubquiz
Version: 0.0.5
Summary: Python utilities for writing pub quizzes
Home-page: https://github.com/elinscott/pubquiz
Download-URL: https://github.com/elinscott/pubquiz/releases
Author: Edward Linscott
Author-email: edwardlinscott@gmail.com
Maintainer: Edward Linscott
Maintainer-email: edwardlinscott@gmail.com
License: MIT
Project-URL: Tracker, https://github.com/elinscott/pubquiz/issues
Project-URL: Source, https://github.com/elinscott/pubquiz
Project-URL: Documentation, https://pubquiz.readthedocs.io
Keywords: snekpack,cookiecutter
Classifier: Development Status :: 1 - Planning
Classifier: Environment :: Console
Classifier: Intended Audience :: Developers
Classifier: License :: OSI Approved :: MIT License
Classifier: Operating System :: OS Independent
Classifier: Framework :: Pytest
Classifier: Framework :: tox
Classifier: Framework :: Sphinx
Classifier: Programming Language :: Python
Classifier: Programming Language :: Python :: 3.8
Classifier: Programming Language :: Python :: 3.9
Classifier: Programming Language :: Python :: 3.10
Classifier: Programming Language :: Python :: 3.11
Classifier: Programming Language :: Python :: 3 :: Only
Requires-Python: >=3.8
License-File: LICENSE
Requires-Dist: more-itertools
Requires-Dist: tqdm
Requires-Dist: click
Requires-Dist: more-click
Requires-Dist: pyyaml
Provides-Extra: docs
Requires-Dist: sphinx (<7.0) ; extra == 'docs'
Requires-Dist: sphinx-rtd-theme ; extra == 'docs'
Requires-Dist: sphinx-click ; extra == 'docs'
Requires-Dist: sphinx-automodapi ; extra == 'docs'
Provides-Extra: tests
Requires-Dist: pytest ; extra == 'tests'
Requires-Dist: coverage ; extra == 'tests'
